fibheap/_init__.py
fibheap/fheap.py
fibheap/node.py
fibheap-0.1.0.dist-info/LICENSE
fibheap-0.1.0.dist-info/METADATA
fibheap-0.1.0.dist-info/WHEEL
fibheap-0.1.0.dist-info/top_level.txt
fibheap-0.1.0.dist-info/RECORD
