Metadata-Version: 2.1
Name: fibheap
Version: 0.1.0
Summary: fibheap
Home-page: https://github.com/quangntran/fibheap
Author: Quang Tran
Author-email: quang.tran@minerva.kgi.edu
License: MIT
Platform: UNKNOWN
Classifier: Programming Language :: Python :: 3
Classifier: License :: OSI Approved :: MIT License
Classifier: Operating System :: OS Independent
